svgScissors/__init__.py
svgScissors/client.py
svgScissors/element.py
svgScissors/operations.py
svgscissors/__init__.py
svgscissors/client.py
svgscissors/element.py
svgscissors/operations.py
svgscissors-0.0.12.dist-info/LICENSE
svgscissors-0.0.12.dist-info/LICENSE.txt
svgscissors-0.0.12.dist-info/METADATA
svgscissors-0.0.12.dist-info/WHEEL
svgscissors-0.0.12.dist-info/top_level.txt
svgscissors-0.0.12.dist-info/RECORD
