Metadata-Version: 2.1
Name: svgscissors
Version: 0.0.12
Summary: Manipulate svg xml to automate data insertion.
Home-page: https://github.com/TheNextGuy32/svgScissors
Author: Oliver Barnum
Author-email: oliverbarnum32@gmail.com
License: UNKNOWN
Download-URL: https://github.com/TheNextGuy32/svgScissors/archive/0.0.7.tar.gz
Platform: UNKNOWN
Classifier: Programming Language :: Python :: 3.7
Classifier: License :: OSI Approved :: GNU General Public License v3 (GPLv3)
Classifier: Operating System :: OS Independent
Requires-Python: >=3.7
Requires-Dist: asyncio
Requires-Dist: ensure
Requires-Dist: svgutils
Requires-Dist: wand
Requires-Dist: mpmath
